ColBertPyterrier.py
ColBertPyterrier-0.0.1.dist-info/DESCRIPTION.rst
ColBertPyterrier-0.0.1.dist-info/METADATA
ColBertPyterrier-0.0.1.dist-info/RECORD
ColBertPyterrier-0.0.1.dist-info/WHEEL
ColBertPyterrier-0.0.1.dist-info/metadata.json
ColBertPyterrier-0.0.1.dist-info/top_level.txt
