Metadata-Version: 2.0
Name: ColBertPyterrier
Version: 0.0.1
Summary: ColBert integrated with Pyterrier
Home-page: UNKNOWN
Author: UNKNOWN
Author-email: UNKNOWN
License: UNKNOWN
Platform: UNKNOWN
